{
  "type": "File",
  "start": 0,
  "end": 435,
  "loc": {
    "start": {
      "line": 1,
      "column": 0
    },
    "end": {
      "line": 19,
      "column": 0
    }
  },
  "program": {
    "type": "Program",
    "start": 0,
    "end": 435,
    "loc": {
      "start": {
        "line": 1,
        "column": 0
      },
      "end": {
        "line": 19,
        "column": 0
      }
    },
    "sourceType": "module",
    "body": [
      {
        "type": "ImportDeclaration",
        "start": 0,
        "end": 39,
        "loc": {
          "start": {
            "line": 1,
            "column": 0
          },
          "end": {
            "line": 1,
            "column": 39
          }
        },
        "specifiers": [
          {
            "type": "ImportDefaultSpecifier",
            "start": 7,
            "end": 16,
            "loc": {
              "start": {
                "line": 1,
                "column": 7
              },
              "end": {
                "line": 1,
                "column": 16
              }
            },
            "local": {
              "type": "Identifier",
              "start": 7,
              "end": 16,
              "loc": {
                "start": {
                  "line": 1,
                  "column": 7
                },
                "end": {
                  "line": 1,
                  "column": 16
                },
                "identifierName": "byte2pair"
              },
              "name": "byte2pair"
            }
          }
        ],
        "source": {
          "type": "StringLiteral",
          "start": 22,
          "end": 38,
          "loc": {
            "start": {
              "line": 1,
              "column": 22
            },
            "end": {
              "line": 1,
              "column": 38
            }
          },
          "extra": {
            "rawValue": "./byte2pair.js",
            "raw": "'./byte2pair.js'"
          },
          "value": "./byte2pair.js"
        }
      },
      {
        "type": "ImportDeclaration",
        "start": 40,
        "end": 95,
        "loc": {
          "start": {
            "line": 2,
            "column": 0
          },
          "end": {
            "line": 2,
            "column": 55
          }
        },
        "specifiers": [
          {
            "type": "ImportDefaultSpecifier",
            "start": 47,
            "end": 64,
            "loc": {
              "start": {
                "line": 2,
                "column": 7
              },
              "end": {
                "line": 2,
                "column": 24
              }
            },
            "local": {
              "type": "Identifier",
              "start": 47,
              "end": 64,
              "loc": {
                "start": {
                  "line": 2,
                  "column": 7
                },
                "end": {
                  "line": 2,
                  "column": 24
                },
                "identifierName": "Base16DecodeError"
              },
              "name": "Base16DecodeError"
            }
          }
        ],
        "source": {
          "type": "StringLiteral",
          "start": 70,
          "end": 94,
          "loc": {
            "start": {
              "line": 2,
              "column": 30
            },
            "end": {
              "line": 2,
              "column": 54
            }
          },
          "extra": {
            "rawValue": "./Base16DecodeError.js",
            "raw": "'./Base16DecodeError.js'"
          },
          "value": "./Base16DecodeError.js"
        }
      },
      {
        "type": "ExportDefaultDeclaration",
        "start": 97,
        "end": 434,
        "loc": {
          "start": {
            "line": 4,
            "column": 0
          },
          "end": {
            "line": 18,
            "column": 1
          }
        },
        "declaration": {
          "type": "FunctionDeclaration",
          "start": 112,
          "end": 434,
          "loc": {
            "start": {
              "line": 4,
              "column": 15
            },
            "end": {
              "line": 18,
              "column": 1
            }
          },
          "id": {
            "type": "Identifier",
            "start": 122,
            "end": 129,
            "loc": {
              "start": {
                "line": 4,
                "column": 25
              },
              "end": {
                "line": 4,
                "column": 32
              },
              "identifierName": "_decode"
            },
            "name": "_decode"
          },
          "generator": true,
          "expression": false,
          "async": false,
          "params": [
            {
              "type": "Identifier",
              "start": 130,
              "end": 135,
              "loc": {
                "start": {
                  "line": 4,
                  "column": 33
                },
                "end": {
                  "line": 4,
                  "column": 38
                },
                "identifierName": "bytes"
              },
              "name": "bytes"
            },
            {
              "type": "AssignmentPattern",
              "start": 137,
              "end": 152,
              "loc": {
                "start": {
                  "line": 4,
                  "column": 40
                },
                "end": {
                  "line": 4,
                  "column": 55
                }
              },
              "left": {
                "type": "Identifier",
                "start": 137,
                "end": 145,
                "loc": {
                  "start": {
                    "line": 4,
                    "column": 40
                  },
                  "end": {
                    "line": 4,
                    "column": 48
                  },
                  "identifierName": "_options"
                },
                "name": "_options"
              },
              "right": {
                "type": "NullLiteral",
                "start": 148,
                "end": 152,
                "loc": {
                  "start": {
                    "line": 4,
                    "column": 51
                  },
                  "end": {
                    "line": 4,
                    "column": 55
                  }
                }
              }
            }
          ],
          "body": {
            "type": "BlockStatement",
            "start": 154,
            "end": 434,
            "loc": {
              "start": {
                "line": 4,
                "column": 57
              },
              "end": {
                "line": 18,
                "column": 1
              }
            },
            "body": [
              {
                "type": "VariableDeclaration",
                "start": 157,
                "end": 171,
                "loc": {
                  "start": {
                    "line": 5,
                    "column": 1
                  },
                  "end": {
                    "line": 5,
                    "column": 15
                  }
                },
                "declarations": [
                  {
                    "type": "VariableDeclarator",
                    "start": 161,
                    "end": 170,
                    "loc": {
                      "start": {
                        "line": 5,
                        "column": 5
                      },
                      "end": {
                        "line": 5,
                        "column": 14
                      }
                    },
                    "id": {
                      "type": "Identifier",
                      "start": 161,
                      "end": 166,
                      "loc": {
                        "start": {
                          "line": 5,
                          "column": 5
                        },
                        "end": {
                          "line": 5,
                          "column": 10
                        },
                        "identifierName": "start"
                      },
                      "name": "start"
                    },
                    "init": {
                      "type": "NumericLiteral",
                      "start": 169,
                      "end": 170,
                      "loc": {
                        "start": {
                          "line": 5,
                          "column": 13
                        },
                        "end": {
                          "line": 5,
                          "column": 14
                        }
                      },
                      "extra": {
                        "rawValue": 0,
                        "raw": "0"
                      },
                      "value": 0
                    }
                  }
                ],
                "kind": "let"
              },
              {
                "type": "ForOfStatement",
                "start": 174,
                "end": 432,
                "loc": {
                  "start": {
                    "line": 7,
                    "column": 1
                  },
                  "end": {
                    "line": 17,
                    "column": 2
                  }
                },
                "left": {
                  "type": "VariableDeclaration",
                  "start": 179,
                  "end": 186,
                  "loc": {
                    "start": {
                      "line": 7,
                      "column": 6
                    },
                    "end": {
                      "line": 7,
                      "column": 13
                    }
                  },
                  "declarations": [
                    {
                      "type": "VariableDeclarator",
                      "start": 185,
                      "end": 186,
                      "loc": {
                        "start": {
                          "line": 7,
                          "column": 12
                        },
                        "end": {
                          "line": 7,
                          "column": 13
                        }
                      },
                      "id": {
                        "type": "Identifier",
                        "start": 185,
                        "end": 186,
                        "loc": {
                          "start": {
                            "line": 7,
                            "column": 12
                          },
                          "end": {
                            "line": 7,
                            "column": 13
                          },
                          "identifierName": "b"
                        },
                        "name": "b"
                      },
                      "init": null
                    }
                  ],
                  "kind": "const"
                },
                "right": {
                  "type": "Identifier",
                  "start": 190,
                  "end": 195,
                  "loc": {
                    "start": {
                      "line": 7,
                      "column": 17
                    },
                    "end": {
                      "line": 7,
                      "column": 22
                    },
                    "identifierName": "bytes"
                  },
                  "name": "bytes"
                },
                "body": {
                  "type": "BlockStatement",
                  "start": 197,
                  "end": 432,
                  "loc": {
                    "start": {
                      "line": 7,
                      "column": 24
                    },
                    "end": {
                      "line": 17,
                      "column": 2
                    }
                  },
                  "body": [
                    {
                      "type": "IfStatement",
                      "start": 201,
                      "end": 394,
                      "loc": {
                        "start": {
                          "line": 8,
                          "column": 2
                        },
                        "end": {
                          "line": 12,
                          "column": 3
                        }
                      },
                      "test": {
                        "type": "LogicalExpression",
                        "start": 205,
                        "end": 225,
                        "loc": {
                          "start": {
                            "line": 8,
                            "column": 6
                          },
                          "end": {
                            "line": 8,
                            "column": 26
                          }
                        },
                        "left": {
                          "type": "BinaryExpression",
                          "start": 205,
                          "end": 213,
                          "loc": {
                            "start": {
                              "line": 8,
                              "column": 6
                            },
                            "end": {
                              "line": 8,
                              "column": 14
                            }
                          },
                          "left": {
                            "type": "Identifier",
                            "start": 205,
                            "end": 206,
                            "loc": {
                              "start": {
                                "line": 8,
                                "column": 6
                              },
                              "end": {
                                "line": 8,
                                "column": 7
                              },
                              "identifierName": "b"
                            },
                            "name": "b"
                          },
                          "operator": "<",
                          "right": {
                            "type": "NumericLiteral",
                            "start": 209,
                            "end": 213,
                            "loc": {
                              "start": {
                                "line": 8,
                                "column": 10
                              },
                              "end": {
                                "line": 8,
                                "column": 14
                              }
                            },
                            "extra": {
                              "rawValue": 0,
                              "raw": "0x00"
                            },
                            "value": 0
                          }
                        },
                        "operator": "||",
                        "right": {
                          "type": "BinaryExpression",
                          "start": 217,
                          "end": 225,
                          "loc": {
                            "start": {
                              "line": 8,
                              "column": 18
                            },
                            "end": {
                              "line": 8,
                              "column": 26
                            }
                          },
                          "left": {
                            "type": "Identifier",
                            "start": 217,
                            "end": 218,
                            "loc": {
                              "start": {
                                "line": 8,
                                "column": 18
                              },
                              "end": {
                                "line": 8,
                                "column": 19
                              },
                              "identifierName": "b"
                            },
                            "name": "b"
                          },
                          "operator": ">",
                          "right": {
                            "type": "NumericLiteral",
                            "start": 221,
                            "end": 225,
                            "loc": {
                              "start": {
                                "line": 8,
                                "column": 22
                              },
                              "end": {
                                "line": 8,
                                "column": 26
                              }
                            },
                            "extra": {
                              "rawValue": 255,
                              "raw": "0xff"
                            },
                            "value": 255
                          }
                        }
                      },
                      "consequent": {
                        "type": "BlockStatement",
                        "start": 227,
                        "end": 394,
                        "loc": {
                          "start": {
                            "line": 8,
                            "column": 28
                          },
                          "end": {
                            "line": 12,
                            "column": 3
                          }
                        },
                        "body": [
                          {
                            "type": "VariableDeclaration",
                            "start": 232,
                            "end": 288,
                            "loc": {
                              "start": {
                                "line": 9,
                                "column": 3
                              },
                              "end": {
                                "line": 9,
                                "column": 59
                              }
                            },
                            "declarations": [
                              {
                                "type": "VariableDeclarator",
                                "start": 238,
                                "end": 287,
                                "loc": {
                                  "start": {
                                    "line": 9,
                                    "column": 9
                                  },
                                  "end": {
                                    "line": 9,
                                    "column": 58
                                  }
                                },
                                "id": {
                                  "type": "Identifier",
                                  "start": 238,
                                  "end": 244,
                                  "loc": {
                                    "start": {
                                      "line": 9,
                                      "column": 9
                                    },
                                    "end": {
                                      "line": 9,
                                      "column": 15
                                    },
                                    "identifierName": "reason"
                                  },
                                  "name": "reason"
                                },
                                "init": {
                                  "type": "TemplateLiteral",
                                  "start": 247,
                                  "end": 287,
                                  "loc": {
                                    "start": {
                                      "line": 9,
                                      "column": 18
                                    },
                                    "end": {
                                      "line": 9,
                                      "column": 58
                                    }
                                  },
                                  "expressions": [
                                    {
                                      "type": "Identifier",
                                      "start": 276,
                                      "end": 277,
                                      "loc": {
                                        "start": {
                                          "line": 9,
                                          "column": 47
                                        },
                                        "end": {
                                          "line": 9,
                                          "column": 48
                                        },
                                        "identifierName": "b"
                                      },
                                      "name": "b"
                                    }
                                  ],
                                  "quasis": [
                                    {
                                      "type": "TemplateElement",
                                      "start": 248,
                                      "end": 274,
                                      "loc": {
                                        "start": {
                                          "line": 9,
                                          "column": 19
                                        },
                                        "end": {
                                          "line": 9,
                                          "column": 45
                                        }
                                      },
                                      "value": {
                                        "raw": "byte out of range 0x00 <= ",
                                        "cooked": "byte out of range 0x00 <= "
                                      },
                                      "tail": false
                                    },
                                    {
                                      "type": "TemplateElement",
                                      "start": 278,
                                      "end": 286,
                                      "loc": {
                                        "start": {
                                          "line": 9,
                                          "column": 49
                                        },
                                        "end": {
                                          "line": 9,
                                          "column": 57
                                        }
                                      },
                                      "value": {
                                        "raw": " <= 0xFF",
                                        "cooked": " <= 0xFF"
                                      },
                                      "tail": true
                                    }
                                  ]
                                }
                              }
                            ],
                            "kind": "const"
                          },
                          {
                            "type": "VariableDeclaration",
                            "start": 292,
                            "end": 333,
                            "loc": {
                              "start": {
                                "line": 10,
                                "column": 3
                              },
                              "end": {
                                "line": 10,
                                "column": 44
                              }
                            },
                            "declarations": [
                              {
                                "type": "VariableDeclarator",
                                "start": 298,
                                "end": 332,
                                "loc": {
                                  "start": {
                                    "line": 10,
                                    "column": 9
                                  },
                                  "end": {
                                    "line": 10,
                                    "column": 43
                                  }
                                },
                                "id": {
                                  "type": "Identifier",
                                  "start": 298,
                                  "end": 306,
                                  "loc": {
                                    "start": {
                                      "line": 10,
                                      "column": 9
                                    },
                                    "end": {
                                      "line": 10,
                                      "column": 17
                                    },
                                    "identifierName": "position"
                                  },
                                  "name": "position"
                                },
                                "init": {
                                  "type": "ObjectExpression",
                                  "start": 309,
                                  "end": 332,
                                  "loc": {
                                    "start": {
                                      "line": 10,
                                      "column": 20
                                    },
                                    "end": {
                                      "line": 10,
                                      "column": 43
                                    }
                                  },
                                  "properties": [
                                    {
                                      "type": "ObjectProperty",
                                      "start": 310,
                                      "end": 315,
                                      "loc": {
                                        "start": {
                                          "line": 10,
                                          "column": 21
                                        },
                                        "end": {
                                          "line": 10,
                                          "column": 26
                                        }
                                      },
                                      "method": false,
                                      "shorthand": true,
                                      "computed": false,
                                      "key": {
                                        "type": "Identifier",
                                        "start": 310,
                                        "end": 315,
                                        "loc": {
                                          "start": {
                                            "line": 10,
                                            "column": 21
                                          },
                                          "end": {
                                            "line": 10,
                                            "column": 26
                                          },
                                          "identifierName": "start"
                                        },
                                        "name": "start"
                                      },
                                      "value": {
                                        "type": "Identifier",
                                        "start": 310,
                                        "end": 315,
                                        "loc": {
                                          "start": {
                                            "line": 10,
                                            "column": 21
                                          },
                                          "end": {
                                            "line": 10,
                                            "column": 26
                                          },
                                          "identifierName": "start"
                                        },
                                        "name": "start"
                                      },
                                      "extra": {
                                        "shorthand": true
                                      }
                                    },
                                    {
                                      "type": "ObjectProperty",
                                      "start": 317,
                                      "end": 331,
                                      "loc": {
                                        "start": {
                                          "line": 10,
                                          "column": 28
                                        },
                                        "end": {
                                          "line": 10,
                                          "column": 42
                                        }
                                      },
                                      "method": false,
                                      "shorthand": false,
                                      "computed": false,
                                      "key": {
                                        "type": "Identifier",
                                        "start": 317,
                                        "end": 320,
                                        "loc": {
                                          "start": {
                                            "line": 10,
                                            "column": 28
                                          },
                                          "end": {
                                            "line": 10,
                                            "column": 31
                                          },
                                          "identifierName": "end"
                                        },
                                        "name": "end"
                                      },
                                      "value": {
                                        "type": "BinaryExpression",
                                        "start": 322,
                                        "end": 331,
                                        "loc": {
                                          "start": {
                                            "line": 10,
                                            "column": 33
                                          },
                                          "end": {
                                            "line": 10,
                                            "column": 42
                                          }
                                        },
                                        "left": {
                                          "type": "Identifier",
                                          "start": 322,
                                          "end": 327,
                                          "loc": {
                                            "start": {
                                              "line": 10,
                                              "column": 33
                                            },
                                            "end": {
                                              "line": 10,
                                              "column": 38
                                            },
                                            "identifierName": "start"
                                          },
                                          "name": "start"
                                        },
                                        "operator": "+",
                                        "right": {
                                          "type": "NumericLiteral",
                                          "start": 330,
                                          "end": 331,
                                          "loc": {
                                            "start": {
                                              "line": 10,
                                              "column": 41
                                            },
                                            "end": {
                                              "line": 10,
                                              "column": 42
                                            }
                                          },
                                          "extra": {
                                            "rawValue": 1,
                                            "raw": "1"
                                          },
                                          "value": 1
                                        }
                                      }
                                    }
                                  ]
                                }
                              }
                            ],
                            "kind": "const"
                          },
                          {
                            "type": "ThrowStatement",
                            "start": 337,
                            "end": 390,
                            "loc": {
                              "start": {
                                "line": 11,
                                "column": 3
                              },
                              "end": {
                                "line": 11,
                                "column": 56
                              }
                            },
                            "argument": {
                              "type": "NewExpression",
                              "start": 343,
                              "end": 389,
                              "loc": {
                                "start": {
                                  "line": 11,
                                  "column": 9
                                },
                                "end": {
                                  "line": 11,
                                  "column": 55
                                }
                              },
                              "callee": {
                                "type": "Identifier",
                                "start": 347,
                                "end": 364,
                                "loc": {
                                  "start": {
                                    "line": 11,
                                    "column": 13
                                  },
                                  "end": {
                                    "line": 11,
                                    "column": 30
                                  },
                                  "identifierName": "Base16DecodeError"
                                },
                                "name": "Base16DecodeError"
                              },
                              "arguments": [
                                {
                                  "type": "Identifier",
                                  "start": 365,
                                  "end": 371,
                                  "loc": {
                                    "start": {
                                      "line": 11,
                                      "column": 31
                                    },
                                    "end": {
                                      "line": 11,
                                      "column": 37
                                    },
                                    "identifierName": "reason"
                                  },
                                  "name": "reason"
                                },
                                {
                                  "type": "Identifier",
                                  "start": 373,
                                  "end": 378,
                                  "loc": {
                                    "start": {
                                      "line": 11,
                                      "column": 39
                                    },
                                    "end": {
                                      "line": 11,
                                      "column": 44
                                    },
                                    "identifierName": "bytes"
                                  },
                                  "name": "bytes"
                                },
                                {
                                  "type": "Identifier",
                                  "start": 380,
                                  "end": 388,
                                  "loc": {
                                    "start": {
                                      "line": 11,
                                      "column": 46
                                    },
                                    "end": {
                                      "line": 11,
                                      "column": 54
                                    },
                                    "identifierName": "position"
                                  },
                                  "name": "position"
                                }
                              ]
                            }
                          }
                        ],
                        "directives": []
                      },
                      "alternate": null
                    },
                    {
                      "type": "ExpressionStatement",
                      "start": 398,
                      "end": 417,
                      "loc": {
                        "start": {
                          "line": 14,
                          "column": 2
                        },
                        "end": {
                          "line": 14,
                          "column": 21
                        }
                      },
                      "expression": {
                        "type": "YieldExpression",
                        "start": 398,
                        "end": 416,
                        "loc": {
                          "start": {
                            "line": 14,
                            "column": 2
                          },
                          "end": {
                            "line": 14,
                            "column": 20
                          }
                        },
                        "delegate": false,
                        "argument": {
                          "type": "MemberExpression",
                          "start": 404,
                          "end": 416,
                          "loc": {
                            "start": {
                              "line": 14,
                              "column": 8
                            },
                            "end": {
                              "line": 14,
                              "column": 20
                            }
                          },
                          "object": {
                            "type": "Identifier",
                            "start": 404,
                            "end": 413,
                            "loc": {
                              "start": {
                                "line": 14,
                                "column": 8
                              },
                              "end": {
                                "line": 14,
                                "column": 17
                              },
                              "identifierName": "byte2pair"
                            },
                            "name": "byte2pair"
                          },
                          "property": {
                            "type": "Identifier",
                            "start": 414,
                            "end": 415,
                            "loc": {
                              "start": {
                                "line": 14,
                                "column": 18
                              },
                              "end": {
                                "line": 14,
                                "column": 19
                              },
                              "identifierName": "b"
                            },
                            "name": "b"
                          },
                          "computed": true
                        }
                      }
                    },
                    {
                      "type": "ExpressionStatement",
                      "start": 421,
                      "end": 429,
                      "loc": {
                        "start": {
                          "line": 16,
                          "column": 2
                        },
                        "end": {
                          "line": 16,
                          "column": 10
                        }
                      },
                      "expression": {
                        "type": "UpdateExpression",
                        "start": 421,
                        "end": 428,
                        "loc": {
                          "start": {
                            "line": 16,
                            "column": 2
                          },
                          "end": {
                            "line": 16,
                            "column": 9
                          }
                        },
                        "operator": "++",
                        "prefix": true,
                        "argument": {
                          "type": "Identifier",
                          "start": 423,
                          "end": 428,
                          "loc": {
                            "start": {
                              "line": 16,
                              "column": 4
                            },
                            "end": {
                              "line": 16,
                              "column": 9
                            },
                            "identifierName": "start"
                          },
                          "name": "start"
                        },
                        "extra": {
                          "parenthesizedArgument": false
                        }
                      }
                    }
                  ],
                  "directives": []
                }
              }
            ],
            "directives": []
          },
          "leadingComments": [],
          "trailingComments": []
        }
      }
    ],
    "directives": []
  },
  "comments": [],
  "tokens": [
    {
      "type": {
        "label": "import",
        "keyword": "import",
        "beforeExpr": false,
        "startsExpr": true,
        "rightAssociative": false,
        "isLoop": false,
        "isAssign": false,
        "prefix": false,
        "postfix": false,
        "binop": null,
        "updateContext": null
      },
      "value": "import",
      "start": 0,
      "end": 6,
      "loc": {
        "start": {
          "line": 1,
          "column": 0
        },
        "end": {
          "line": 1,
          "column": 6
        }
      }
    },
    {
      "type": {
        "label": "name",
        "beforeExpr": false,
        "startsExpr": true,
        "rightAssociative": false,
        "isLoop": false,
        "isAssign": false,
        "prefix": false,
        "postfix": false,
        "binop": null
      },
      "value": "byte2pair",
      "start": 7,
      "end": 16,
      "loc": {
        "start": {
          "line": 1,
          "column": 7
        },
        "end": {
          "line": 1,
          "column": 16
        }
      }
    },
    {
      "type": {
        "label": "name",
        "beforeExpr": false,
        "startsExpr": true,
        "rightAssociative": false,
        "isLoop": false,
        "isAssign": false,
        "prefix": false,
        "postfix": false,
        "binop": null
      },
      "value": "from",
      "start": 17,
      "end": 21,
      "loc": {
        "start": {
          "line": 1,
          "column": 17
        },
        "end": {
          "line": 1,
          "column": 21
        }
      }
    },
    {
      "type": {
        "label": "string",
        "beforeExpr": false,
        "startsExpr": true,
        "rightAssociative": false,
        "isLoop": false,
        "isAssign": false,
        "prefix": false,
        "postfix": false,
        "binop": null,
        "updateContext": null
      },
      "value": "./byte2pair.js",
      "start": 22,
      "end": 38,
      "loc": {
        "start": {
          "line": 1,
          "column": 22
        },
        "end": {
          "line": 1,
          "column": 38
        }
      }
    },
    {
      "type": {
        "label": ";",
        "beforeExpr": true,
        "startsExpr": false,
        "rightAssociative": false,
        "isLoop": false,
        "isAssign": false,
        "prefix": false,
        "postfix": false,
        "binop": null,
        "updateContext": null
      },
      "start": 38,
      "end": 39,
      "loc": {
        "start": {
          "line": 1,
          "column": 38
        },
        "end": {
          "line": 1,
          "column": 39
        }
      }
    },
    {
      "type": {
        "label": "import",
        "keyword": "import",
        "beforeExpr": false,
        "startsExpr": true,
        "rightAssociative": false,
        "isLoop": false,
        "isAssign": false,
        "prefix": false,
        "postfix": false,
        "binop": null,
        "updateContext": null
      },
      "value": "import",
      "start": 40,
      "end": 46,
      "loc": {
        "start": {
          "line": 2,
          "column": 0
        },
        "end": {
          "line": 2,
          "column": 6
        }
      }
    },
    {
      "type": {
        "label": "name",
        "beforeExpr": false,
        "startsExpr": true,
        "rightAssociative": false,
        "isLoop": false,
        "isAssign": false,
        "prefix": false,
        "postfix": false,
        "binop": null
      },
      "value": "Base16DecodeError",
      "start": 47,
      "end": 64,
      "loc": {
        "start": {
          "line": 2,
          "column": 7
        },
        "end": {
          "line": 2,
          "column": 24
        }
      }
    },
    {
      "type": {
        "label": "name",
        "beforeExpr": false,
        "startsExpr": true,
        "rightAssociative": false,
        "isLoop": false,
        "isAssign": false,
        "prefix": false,
        "postfix": false,
        "binop": null
      },
      "value": "from",
      "start": 65,
      "end": 69,
      "loc": {
        "start": {
          "line": 2,
          "column": 25
        },
        "end": {
          "line": 2,
          "column": 29
        }
      }
    },
    {
      "type": {
        "label": "string",
        "beforeExpr": false,
        "startsExpr": true,
        "rightAssociative": false,
        "isLoop": false,
        "isAssign": false,
        "prefix": false,
        "postfix": false,
        "binop": null,
        "updateContext": null
      },
      "value": "./Base16DecodeError.js",
      "start": 70,
      "end": 94,
      "loc": {
        "start": {
          "line": 2,
          "column": 30
        },
        "end": {
          "line": 2,
          "column": 54
        }
      }
    },
    {
      "type": {
        "label": ";",
        "beforeExpr": true,
        "startsExpr": false,
        "rightAssociative": false,
        "isLoop": false,
        "isAssign": false,
        "prefix": false,
        "postfix": false,
        "binop": null,
        "updateContext": null
      },
      "start": 94,
      "end": 95,
      "loc": {
        "start": {
          "line": 2,
          "column": 54
        },
        "end": {
          "line": 2,
          "column": 55
        }
      }
    },
    {
      "type": {
        "label": "export",
        "keyword": "export",
        "beforeExpr": false,
        "startsExpr": false,
        "rightAssociative": false,
        "isLoop": false,
        "isAssign": false,
        "prefix": false,
        "postfix": false,
        "binop": null,
        "updateContext": null
      },
      "value": "export",
      "start": 97,
      "end": 103,
      "loc": {
        "start": {
          "line": 4,
          "column": 0
        },
        "end": {
          "line": 4,
          "column": 6
        }
      }
    },
    {
      "type": {
        "label": "default",
        "keyword": "default",
        "beforeExpr": true,
        "startsExpr": false,
        "rightAssociative": false,
        "isLoop": false,
        "isAssign": false,
        "prefix": false,
        "postfix": false,
        "binop": null,
        "updateContext": null
      },
      "value": "default",
      "start": 104,
      "end": 111,
      "loc": {
        "start": {
          "line": 4,
          "column": 7
        },
        "end": {
          "line": 4,
          "column": 14
        }
      }
    },
    {
      "type": {
        "label": "function",
        "keyword": "function",
        "beforeExpr": false,
        "startsExpr": true,
        "rightAssociative": false,
        "isLoop": false,
        "isAssign": false,
        "prefix": false,
        "postfix": false,
        "binop": null
      },
      "value": "function",
      "start": 112,
      "end": 120,
      "loc": {
        "start": {
          "line": 4,
          "column": 15
        },
        "end": {
          "line": 4,
          "column": 23
        }
      }
    },
    {
      "type": {
        "label": "*",
        "beforeExpr": true,
        "startsExpr": false,
        "rightAssociative": false,
        "isLoop": false,
        "isAssign": false,
        "prefix": false,
        "postfix": false,
        "binop": 10,
        "updateContext": null
      },
      "value": "*",
      "start": 120,
      "end": 121,
      "loc": {
        "start": {
          "line": 4,
          "column": 23
        },
        "end": {
          "line": 4,
          "column": 24
        }
      }
    },
    {
      "type": {
        "label": "name",
        "beforeExpr": false,
        "startsExpr": true,
        "rightAssociative": false,
        "isLoop": false,
        "isAssign": false,
        "prefix": false,
        "postfix": false,
        "binop": null
      },
      "value": "_decode",
      "start": 122,
      "end": 129,
      "loc": {
        "start": {
          "line": 4,
          "column": 25
        },
        "end": {
          "line": 4,
          "column": 32
        }
      }
    },
    {
      "type": {
        "label": "(",
        "beforeExpr": true,
        "startsExpr": true,
        "rightAssociative": false,
        "isLoop": false,
        "isAssign": false,
        "prefix": false,
        "postfix": false,
        "binop": null
      },
      "start": 129,
      "end": 130,
      "loc": {
        "start": {
          "line": 4,
          "column": 32
        },
        "end": {
          "line": 4,
          "column": 33
        }
      }
    },
    {
      "type": {
        "label": "name",
        "beforeExpr": false,
        "startsExpr": true,
        "rightAssociative": false,
        "isLoop": false,
        "isAssign": false,
        "prefix": false,
        "postfix": false,
        "binop": null
      },
      "value": "bytes",
      "start": 130,
      "end": 135,
      "loc": {
        "start": {
          "line": 4,
          "column": 33
        },
        "end": {
          "line": 4,
          "column": 38
        }
      }
    },
    {
      "type": {
        "label": ",",
        "beforeExpr": true,
        "startsExpr": false,
        "rightAssociative": false,
        "isLoop": false,
        "isAssign": false,
        "prefix": false,
        "postfix": false,
        "binop": null,
        "updateContext": null
      },
      "start": 135,
      "end": 136,
      "loc": {
        "start": {
          "line": 4,
          "column": 38
        },
        "end": {
          "line": 4,
          "column": 39
        }
      }
    },
    {
      "type": {
        "label": "name",
        "beforeExpr": false,
        "startsExpr": true,
        "rightAssociative": false,
        "isLoop": false,
        "isAssign": false,
        "prefix": false,
        "postfix": false,
        "binop": null
      },
      "value": "_options",
      "start": 137,
      "end": 145,
      "loc": {
        "start": {
          "line": 4,
          "column": 40
        },
        "end": {
          "line": 4,
          "column": 48
        }
      }
    },
    {
      "type": {
        "label": "=",
        "beforeExpr": true,
        "startsExpr": false,
        "rightAssociative": false,
        "isLoop": false,
        "isAssign": true,
        "prefix": false,
        "postfix": false,
        "binop": null,
        "updateContext": null
      },
      "value": "=",
      "start": 146,
      "end": 147,
      "loc": {
        "start": {
          "line": 4,
          "column": 49
        },
        "end": {
          "line": 4,
          "column": 50
        }
      }
    },
    {
      "type": {
        "label": "null",
        "keyword": "null",
        "beforeExpr": false,
        "startsExpr": true,
        "rightAssociative": false,
        "isLoop": false,
        "isAssign": false,
        "prefix": false,
        "postfix": false,
        "binop": null,
        "updateContext": null
      },
      "value": "null",
      "start": 148,
      "end": 152,
      "loc": {
        "start": {
          "line": 4,
          "column": 51
        },
        "end": {
          "line": 4,
          "column": 55
        }
      }
    },
    {
      "type": {
        "label": ")",
        "beforeExpr": false,
        "startsExpr": false,
        "rightAssociative": false,
        "isLoop": false,
        "isAssign": false,
        "prefix": false,
        "postfix": false,
        "binop": null
      },
      "start": 152,
      "end": 153,
      "loc": {
        "start": {
          "line": 4,
          "column": 55
        },
        "end": {
          "line": 4,
          "column": 56
        }
      }
    },
    {
      "type": {
        "label": "{",
        "beforeExpr": true,
        "startsExpr": true,
        "rightAssociative": false,
        "isLoop": false,
        "isAssign": false,
        "prefix": false,
        "postfix": false,
        "binop": null
      },
      "start": 154,
      "end": 155,
      "loc": {
        "start": {
          "line": 4,
          "column": 57
        },
        "end": {
          "line": 4,
          "column": 58
        }
      }
    },
    {
      "type": {
        "label": "let",
        "keyword": "let",
        "beforeExpr": false,
        "startsExpr": false,
        "rightAssociative": false,
        "isLoop": false,
        "isAssign": false,
        "prefix": false,
        "postfix": false,
        "binop": null,
        "updateContext": null
      },
      "value": "let",
      "start": 157,
      "end": 160,
      "loc": {
        "start": {
          "line": 5,
          "column": 1
        },
        "end": {
          "line": 5,
          "column": 4
        }
      }
    },
    {
      "type": {
        "label": "name",
        "beforeExpr": false,
        "startsExpr": true,
        "rightAssociative": false,
        "isLoop": false,
        "isAssign": false,
        "prefix": false,
        "postfix": false,
        "binop": null
      },
      "value": "start",
      "start": 161,
      "end": 166,
      "loc": {
        "start": {
          "line": 5,
          "column": 5
        },
        "end": {
          "line": 5,
          "column": 10
        }
      }
    },
    {
      "type": {
        "label": "=",
        "beforeExpr": true,
        "startsExpr": false,
        "rightAssociative": false,
        "isLoop": false,
        "isAssign": true,
        "prefix": false,
        "postfix": false,
        "binop": null,
        "updateContext": null
      },
      "value": "=",
      "start": 167,
      "end": 168,
      "loc": {
        "start": {
          "line": 5,
          "column": 11
        },
        "end": {
          "line": 5,
          "column": 12
        }
      }
    },
    {
      "type": {
        "label": "num",
        "beforeExpr": false,
        "startsExpr": true,
        "rightAssociative": false,
        "isLoop": false,
        "isAssign": false,
        "prefix": false,
        "postfix": false,
        "binop": null,
        "updateContext": null
      },
      "value": 0,
      "start": 169,
      "end": 170,
      "loc": {
        "start": {
          "line": 5,
          "column": 13
        },
        "end": {
          "line": 5,
          "column": 14
        }
      }
    },
    {
      "type": {
        "label": ";",
        "beforeExpr": true,
        "startsExpr": false,
        "rightAssociative": false,
        "isLoop": false,
        "isAssign": false,
        "prefix": false,
        "postfix": false,
        "binop": null,
        "updateContext": null
      },
      "start": 170,
      "end": 171,
      "loc": {
        "start": {
          "line": 5,
          "column": 14
        },
        "end": {
          "line": 5,
          "column": 15
        }
      }
    },
    {
      "type": {
        "label": "for",
        "keyword": "for",
        "beforeExpr": false,
        "startsExpr": false,
        "rightAssociative": false,
        "isLoop": true,
        "isAssign": false,
        "prefix": false,
        "postfix": false,
        "binop": null,
        "updateContext": null
      },
      "value": "for",
      "start": 174,
      "end": 177,
      "loc": {
        "start": {
          "line": 7,
          "column": 1
        },
        "end": {
          "line": 7,
          "column": 4
        }
      }
    },
    {
      "type": {
        "label": "(",
        "beforeExpr": true,
        "startsExpr": true,
        "rightAssociative": false,
        "isLoop": false,
        "isAssign": false,
        "prefix": false,
        "postfix": false,
        "binop": null
      },
      "start": 178,
      "end": 179,
      "loc": {
        "start": {
          "line": 7,
          "column": 5
        },
        "end": {
          "line": 7,
          "column": 6
        }
      }
    },
    {
      "type": {
        "label": "const",
        "keyword": "const",
        "beforeExpr": false,
        "startsExpr": false,
        "rightAssociative": false,
        "isLoop": false,
        "isAssign": false,
        "prefix": false,
        "postfix": false,
        "binop": null,
        "updateContext": null
      },
      "value": "const",
      "start": 179,
      "end": 184,
      "loc": {
        "start": {
          "line": 7,
          "column": 6
        },
        "end": {
          "line": 7,
          "column": 11
        }
      }
    },
    {
      "type": {
        "label": "name",
        "beforeExpr": false,
        "startsExpr": true,
        "rightAssociative": false,
        "isLoop": false,
        "isAssign": false,
        "prefix": false,
        "postfix": false,
        "binop": null
      },
      "value": "b",
      "start": 185,
      "end": 186,
      "loc": {
        "start": {
          "line": 7,
          "column": 12
        },
        "end": {
          "line": 7,
          "column": 13
        }
      }
    },
    {
      "type": {
        "label": "name",
        "beforeExpr": false,
        "startsExpr": true,
        "rightAssociative": false,
        "isLoop": false,
        "isAssign": false,
        "prefix": false,
        "postfix": false,
        "binop": null
      },
      "value": "of",
      "start": 187,
      "end": 189,
      "loc": {
        "start": {
          "line": 7,
          "column": 14
        },
        "end": {
          "line": 7,
          "column": 16
        }
      }
    },
    {
      "type": {
        "label": "name",
        "beforeExpr": false,
        "startsExpr": true,
        "rightAssociative": false,
        "isLoop": false,
        "isAssign": false,
        "prefix": false,
        "postfix": false,
        "binop": null
      },
      "value": "bytes",
      "start": 190,
      "end": 195,
      "loc": {
        "start": {
          "line": 7,
          "column": 17
        },
        "end": {
          "line": 7,
          "column": 22
        }
      }
    },
    {
      "type": {
        "label": ")",
        "beforeExpr": false,
        "startsExpr": false,
        "rightAssociative": false,
        "isLoop": false,
        "isAssign": false,
        "prefix": false,
        "postfix": false,
        "binop": null
      },
      "start": 195,
      "end": 196,
      "loc": {
        "start": {
          "line": 7,
          "column": 22
        },
        "end": {
          "line": 7,
          "column": 23
        }
      }
    },
    {
      "type": {
        "label": "{",
        "beforeExpr": true,
        "startsExpr": true,
        "rightAssociative": false,
        "isLoop": false,
        "isAssign": false,
        "prefix": false,
        "postfix": false,
        "binop": null
      },
      "start": 197,
      "end": 198,
      "loc": {
        "start": {
          "line": 7,
          "column": 24
        },
        "end": {
          "line": 7,
          "column": 25
        }
      }
    },
    {
      "type": {
        "label": "if",
        "keyword": "if",
        "beforeExpr": false,
        "startsExpr": false,
        "rightAssociative": false,
        "isLoop": false,
        "isAssign": false,
        "prefix": false,
        "postfix": false,
        "binop": null,
        "updateContext": null
      },
      "value": "if",
      "start": 201,
      "end": 203,
      "loc": {
        "start": {
          "line": 8,
          "column": 2
        },
        "end": {
          "line": 8,
          "column": 4
        }
      }
    },
    {
      "type": {
        "label": "(",
        "beforeExpr": true,
        "startsExpr": true,
        "rightAssociative": false,
        "isLoop": false,
        "isAssign": false,
        "prefix": false,
        "postfix": false,
        "binop": null
      },
      "start": 204,
      "end": 205,
      "loc": {
        "start": {
          "line": 8,
          "column": 5
        },
        "end": {
          "line": 8,
          "column": 6
        }
      }
    },
    {
      "type": {
        "label": "name",
        "beforeExpr": false,
        "startsExpr": true,
        "rightAssociative": false,
        "isLoop": false,
        "isAssign": false,
        "prefix": false,
        "postfix": false,
        "binop": null
      },
      "value": "b",
      "start": 205,
      "end": 206,
      "loc": {
        "start": {
          "line": 8,
          "column": 6
        },
        "end": {
          "line": 8,
          "column": 7
        }
      }
    },
    {
      "type": {
        "label": "</>",
        "beforeExpr": true,
        "startsExpr": false,
        "rightAssociative": false,
        "isLoop": false,
        "isAssign": false,
        "prefix": false,
        "postfix": false,
        "binop": 7,
        "updateContext": null
      },
      "value": "<",
      "start": 207,
      "end": 208,
      "loc": {
        "start": {
          "line": 8,
          "column": 8
        },
        "end": {
          "line": 8,
          "column": 9
        }
      }
    },
    {
      "type": {
        "label": "num",
        "beforeExpr": false,
        "startsExpr": true,
        "rightAssociative": false,
        "isLoop": false,
        "isAssign": false,
        "prefix": false,
        "postfix": false,
        "binop": null,
        "updateContext": null
      },
      "value": 0,
      "start": 209,
      "end": 213,
      "loc": {
        "start": {
          "line": 8,
          "column": 10
        },
        "end": {
          "line": 8,
          "column": 14
        }
      }
    },
    {
      "type": {
        "label": "||",
        "beforeExpr": true,
        "startsExpr": false,
        "rightAssociative": false,
        "isLoop": false,
        "isAssign": false,
        "prefix": false,
        "postfix": false,
        "binop": 1,
        "updateContext": null
      },
      "value": "||",
      "start": 214,
      "end": 216,
      "loc": {
        "start": {
          "line": 8,
          "column": 15
        },
        "end": {
          "line": 8,
          "column": 17
        }
      }
    },
    {
      "type": {
        "label": "name",
        "beforeExpr": false,
        "startsExpr": true,
        "rightAssociative": false,
        "isLoop": false,
        "isAssign": false,
        "prefix": false,
        "postfix": false,
        "binop": null
      },
      "value": "b",
      "start": 217,
      "end": 218,
      "loc": {
        "start": {
          "line": 8,
          "column": 18
        },
        "end": {
          "line": 8,
          "column": 19
        }
      }
    },
    {
      "type": {
        "label": "</>",
        "beforeExpr": true,
        "startsExpr": false,
        "rightAssociative": false,
        "isLoop": false,
        "isAssign": false,
        "prefix": false,
        "postfix": false,
        "binop": 7,
        "updateContext": null
      },
      "value": ">",
      "start": 219,
      "end": 220,
      "loc": {
        "start": {
          "line": 8,
          "column": 20
        },
        "end": {
          "line": 8,
          "column": 21
        }
      }
    },
    {
      "type": {
        "label": "num",
        "beforeExpr": false,
        "startsExpr": true,
        "rightAssociative": false,
        "isLoop": false,
        "isAssign": false,
        "prefix": false,
        "postfix": false,
        "binop": null,
        "updateContext": null
      },
      "value": 255,
      "start": 221,
      "end": 225,
      "loc": {
        "start": {
          "line": 8,
          "column": 22
        },
        "end": {
          "line": 8,
          "column": 26
        }
      }
    },
    {
      "type": {
        "label": ")",
        "beforeExpr": false,
        "startsExpr": false,
        "rightAssociative": false,
        "isLoop": false,
        "isAssign": false,
        "prefix": false,
        "postfix": false,
        "binop": null
      },
      "start": 225,
      "end": 226,
      "loc": {
        "start": {
          "line": 8,
          "column": 26
        },
        "end": {
          "line": 8,
          "column": 27
        }
      }
    },
    {
      "type": {
        "label": "{",
        "beforeExpr": true,
        "startsExpr": true,
        "rightAssociative": false,
        "isLoop": false,
        "isAssign": false,
        "prefix": false,
        "postfix": false,
        "binop": null
      },
      "start": 227,
      "end": 228,
      "loc": {
        "start": {
          "line": 8,
          "column": 28
        },
        "end": {
          "line": 8,
          "column": 29
        }
      }
    },
    {
      "type": {
        "label": "const",
        "keyword": "const",
        "beforeExpr": false,
        "startsExpr": false,
        "rightAssociative": false,
        "isLoop": false,
        "isAssign": false,
        "prefix": false,
        "postfix": false,
        "binop": null,
        "updateContext": null
      },
      "value": "const",
      "start": 232,
      "end": 237,
      "loc": {
        "start": {
          "line": 9,
          "column": 3
        },
        "end": {
          "line": 9,
          "column": 8
        }
      }
    },
    {
      "type": {
        "label": "name",
        "beforeExpr": false,
        "startsExpr": true,
        "rightAssociative": false,
        "isLoop": false,
        "isAssign": false,
        "prefix": false,
        "postfix": false,
        "binop": null
      },
      "value": "reason",
      "start": 238,
      "end": 244,
      "loc": {
        "start": {
          "line": 9,
          "column": 9
        },
        "end": {
          "line": 9,
          "column": 15
        }
      }
    },
    {
      "type": {
        "label": "=",
        "beforeExpr": true,
        "startsExpr": false,
        "rightAssociative": false,
        "isLoop": false,
        "isAssign": true,
        "prefix": false,
        "postfix": false,
        "binop": null,
        "updateContext": null
      },
      "value": "=",
      "start": 245,
      "end": 246,
      "loc": {
        "start": {
          "line": 9,
          "column": 16
        },
        "end": {
          "line": 9,
          "column": 17
        }
      }
    },
    {
      "type": {
        "label": "`",
        "beforeExpr": false,
        "startsExpr": true,
        "rightAssociative": false,
        "isLoop": false,
        "isAssign": false,
        "prefix": false,
        "postfix": false,
        "binop": null
      },
      "start": 247,
      "end": 248,
      "loc": {
        "start": {
          "line": 9,
          "column": 18
        },
        "end": {
          "line": 9,
          "column": 19
        }
      }
    },
    {
      "type": {
        "label": "template",
        "beforeExpr": false,
        "startsExpr": false,
        "rightAssociative": false,
        "isLoop": false,
        "isAssign": false,
        "prefix": false,
        "postfix": false,
        "binop": null,
        "updateContext": null
      },
      "value": "byte out of range 0x00 <= ",
      "start": 248,
      "end": 274,
      "loc": {
        "start": {
          "line": 9,
          "column": 19
        },
        "end": {
          "line": 9,
          "column": 45
        }
      }
    },
    {
      "type": {
        "label": "${",
        "beforeExpr": true,
        "startsExpr": true,
        "rightAssociative": false,
        "isLoop": false,
        "isAssign": false,
        "prefix": false,
        "postfix": false,
        "binop": null
      },
      "start": 274,
      "end": 276,
      "loc": {
        "start": {
          "line": 9,
          "column": 45
        },
        "end": {
          "line": 9,
          "column": 47
        }
      }
    },
    {
      "type": {
        "label": "name",
        "beforeExpr": false,
        "startsExpr": true,
        "rightAssociative": false,
        "isLoop": false,
        "isAssign": false,
        "prefix": false,
        "postfix": false,
        "binop": null
      },
      "value": "b",
      "start": 276,
      "end": 277,
      "loc": {
        "start": {
          "line": 9,
          "column": 47
        },
        "end": {
          "line": 9,
          "column": 48
        }
      }
    },
    {
      "type": {
        "label": "}",
        "beforeExpr": false,
        "startsExpr": false,
        "rightAssociative": false,
        "isLoop": false,
        "isAssign": false,
        "prefix": false,
        "postfix": false,
        "binop": null
      },
      "start": 277,
      "end": 278,
      "loc": {
        "start": {
          "line": 9,
          "column": 48
        },
        "end": {
          "line": 9,
          "column": 49
        }
      }
    },
    {
      "type": {
        "label": "template",
        "beforeExpr": false,
        "startsExpr": false,
        "rightAssociative": false,
        "isLoop": false,
        "isAssign": false,
        "prefix": false,
        "postfix": false,
        "binop": null,
        "updateContext": null
      },
      "value": " <= 0xFF",
      "start": 278,
      "end": 286,
      "loc": {
        "start": {
          "line": 9,
          "column": 49
        },
        "end": {
          "line": 9,
          "column": 57
        }
      }
    },
    {
      "type": {
        "label": "`",
        "beforeExpr": false,
        "startsExpr": true,
        "rightAssociative": false,
        "isLoop": false,
        "isAssign": false,
        "prefix": false,
        "postfix": false,
        "binop": null
      },
      "start": 286,
      "end": 287,
      "loc": {
        "start": {
          "line": 9,
          "column": 57
        },
        "end": {
          "line": 9,
          "column": 58
        }
      }
    },
    {
      "type": {
        "label": ";",
        "beforeExpr": true,
        "startsExpr": false,
        "rightAssociative": false,
        "isLoop": false,
        "isAssign": false,
        "prefix": false,
        "postfix": false,
        "binop": null,
        "updateContext": null
      },
      "start": 287,
      "end": 288,
      "loc": {
        "start": {
          "line": 9,
          "column": 58
        },
        "end": {
          "line": 9,
          "column": 59
        }
      }
    },
    {
      "type": {
        "label": "const",
        "keyword": "const",
        "beforeExpr": false,
        "startsExpr": false,
        "rightAssociative": false,
        "isLoop": false,
        "isAssign": false,
        "prefix": false,
        "postfix": false,
        "binop": null,
        "updateContext": null
      },
      "value": "const",
      "start": 292,
      "end": 297,
      "loc": {
        "start": {
          "line": 10,
          "column": 3
        },
        "end": {
          "line": 10,
          "column": 8
        }
      }
    },
    {
      "type": {
        "label": "name",
        "beforeExpr": false,
        "startsExpr": true,
        "rightAssociative": false,
        "isLoop": false,
        "isAssign": false,
        "prefix": false,
        "postfix": false,
        "binop": null
      },
      "value": "position",
      "start": 298,
      "end": 306,
      "loc": {
        "start": {
          "line": 10,
          "column": 9
        },
        "end": {
          "line": 10,
          "column": 17
        }
      }
    },
    {
      "type": {
        "label": "=",
        "beforeExpr": true,
        "startsExpr": false,
        "rightAssociative": false,
        "isLoop": false,
        "isAssign": true,
        "prefix": false,
        "postfix": false,
        "binop": null,
        "updateContext": null
      },
      "value": "=",
      "start": 307,
      "end": 308,
      "loc": {
        "start": {
          "line": 10,
          "column": 18
        },
        "end": {
          "line": 10,
          "column": 19
        }
      }
    },
    {
      "type": {
        "label": "{",
        "beforeExpr": true,
        "startsExpr": true,
        "rightAssociative": false,
        "isLoop": false,
        "isAssign": false,
        "prefix": false,
        "postfix": false,
        "binop": null
      },
      "start": 309,
      "end": 310,
      "loc": {
        "start": {
          "line": 10,
          "column": 20
        },
        "end": {
          "line": 10,
          "column": 21
        }
      }
    },
    {
      "type": {
        "label": "name",
        "beforeExpr": false,
        "startsExpr": true,
        "rightAssociative": false,
        "isLoop": false,
        "isAssign": false,
        "prefix": false,
        "postfix": false,
        "binop": null
      },
      "value": "start",
      "start": 310,
      "end": 315,
      "loc": {
        "start": {
          "line": 10,
          "column": 21
        },
        "end": {
          "line": 10,
          "column": 26
        }
      }
    },
    {
      "type": {
        "label": ",",
        "beforeExpr": true,
        "startsExpr": false,
        "rightAssociative": false,
        "isLoop": false,
        "isAssign": false,
        "prefix": false,
        "postfix": false,
        "binop": null,
        "updateContext": null
      },
      "start": 315,
      "end": 316,
      "loc": {
        "start": {
          "line": 10,
          "column": 26
        },
        "end": {
          "line": 10,
          "column": 27
        }
      }
    },
    {
      "type": {
        "label": "name",
        "beforeExpr": false,
        "startsExpr": true,
        "rightAssociative": false,
        "isLoop": false,
        "isAssign": false,
        "prefix": false,
        "postfix": false,
        "binop": null
      },
      "value": "end",
      "start": 317,
      "end": 320,
      "loc": {
        "start": {
          "line": 10,
          "column": 28
        },
        "end": {
          "line": 10,
          "column": 31
        }
      }
    },
    {
      "type": {
        "label": ":",
        "beforeExpr": true,
        "startsExpr": false,
        "rightAssociative": false,
        "isLoop": false,
        "isAssign": false,
        "prefix": false,
        "postfix": false,
        "binop": null,
        "updateContext": null
      },
      "start": 320,
      "end": 321,
      "loc": {
        "start": {
          "line": 10,
          "column": 31
        },
        "end": {
          "line": 10,
          "column": 32
        }
      }
    },
    {
      "type": {
        "label": "name",
        "beforeExpr": false,
        "startsExpr": true,
        "rightAssociative": false,
        "isLoop": false,
        "isAssign": false,
        "prefix": false,
        "postfix": false,
        "binop": null
      },
      "value": "start",
      "start": 322,
      "end": 327,
      "loc": {
        "start": {
          "line": 10,
          "column": 33
        },
        "end": {
          "line": 10,
          "column": 38
        }
      }
    },
    {
      "type": {
        "label": "+/-",
        "beforeExpr": true,
        "startsExpr": true,
        "rightAssociative": false,
        "isLoop": false,
        "isAssign": false,
        "prefix": true,
        "postfix": false,
        "binop": 9,
        "updateContext": null
      },
      "value": "+",
      "start": 328,
      "end": 329,
      "loc": {
        "start": {
          "line": 10,
          "column": 39
        },
        "end": {
          "line": 10,
          "column": 40
        }
      }
    },
    {
      "type": {
        "label": "num",
        "beforeExpr": false,
        "startsExpr": true,
        "rightAssociative": false,
        "isLoop": false,
        "isAssign": false,
        "prefix": false,
        "postfix": false,
        "binop": null,
        "updateContext": null
      },
      "value": 1,
      "start": 330,
      "end": 331,
      "loc": {
        "start": {
          "line": 10,
          "column": 41
        },
        "end": {
          "line": 10,
          "column": 42
        }
      }
    },
    {
      "type": {
        "label": "}",
        "beforeExpr": false,
        "startsExpr": false,
        "rightAssociative": false,
        "isLoop": false,
        "isAssign": false,
        "prefix": false,
        "postfix": false,
        "binop": null
      },
      "start": 331,
      "end": 332,
      "loc": {
        "start": {
          "line": 10,
          "column": 42
        },
        "end": {
          "line": 10,
          "column": 43
        }
      }
    },
    {
      "type": {
        "label": ";",
        "beforeExpr": true,
        "startsExpr": false,
        "rightAssociative": false,
        "isLoop": false,
        "isAssign": false,
        "prefix": false,
        "postfix": false,
        "binop": null,
        "updateContext": null
      },
      "start": 332,
      "end": 333,
      "loc": {
        "start": {
          "line": 10,
          "column": 43
        },
        "end": {
          "line": 10,
          "column": 44
        }
      }
    },
    {
      "type": {
        "label": "throw",
        "keyword": "throw",
        "beforeExpr": true,
        "startsExpr": false,
        "rightAssociative": false,
        "isLoop": false,
        "isAssign": false,
        "prefix": false,
        "postfix": false,
        "binop": null,
        "updateContext": null
      },
      "value": "throw",
      "start": 337,
      "end": 342,
      "loc": {
        "start": {
          "line": 11,
          "column": 3
        },
        "end": {
          "line": 11,
          "column": 8
        }
      }
    },
    {
      "type": {
        "label": "new",
        "keyword": "new",
        "beforeExpr": true,
        "startsExpr": true,
        "rightAssociative": false,
        "isLoop": false,
        "isAssign": false,
        "prefix": false,
        "postfix": false,
        "binop": null,
        "updateContext": null
      },
      "value": "new",
      "start": 343,
      "end": 346,
      "loc": {
        "start": {
          "line": 11,
          "column": 9
        },
        "end": {
          "line": 11,
          "column": 12
        }
      }
    },
    {
      "type": {
        "label": "name",
        "beforeExpr": false,
        "startsExpr": true,
        "rightAssociative": false,
        "isLoop": false,
        "isAssign": false,
        "prefix": false,
        "postfix": false,
        "binop": null
      },
      "value": "Base16DecodeError",
      "start": 347,
      "end": 364,
      "loc": {
        "start": {
          "line": 11,
          "column": 13
        },
        "end": {
          "line": 11,
          "column": 30
        }
      }
    },
    {
      "type": {
        "label": "(",
        "beforeExpr": true,
        "startsExpr": true,
        "rightAssociative": false,
        "isLoop": false,
        "isAssign": false,
        "prefix": false,
        "postfix": false,
        "binop": null
      },
      "start": 364,
      "end": 365,
      "loc": {
        "start": {
          "line": 11,
          "column": 30
        },
        "end": {
          "line": 11,
          "column": 31
        }
      }
    },
    {
      "type": {
        "label": "name",
        "beforeExpr": false,
        "startsExpr": true,
        "rightAssociative": false,
        "isLoop": false,
        "isAssign": false,
        "prefix": false,
        "postfix": false,
        "binop": null
      },
      "value": "reason",
      "start": 365,
      "end": 371,
      "loc": {
        "start": {
          "line": 11,
          "column": 31
        },
        "end": {
          "line": 11,
          "column": 37
        }
      }
    },
    {
      "type": {
        "label": ",",
        "beforeExpr": true,
        "startsExpr": false,
        "rightAssociative": false,
        "isLoop": false,
        "isAssign": false,
        "prefix": false,
        "postfix": false,
        "binop": null,
        "updateContext": null
      },
      "start": 371,
      "end": 372,
      "loc": {
        "start": {
          "line": 11,
          "column": 37
        },
        "end": {
          "line": 11,
          "column": 38
        }
      }
    },
    {
      "type": {
        "label": "name",
        "beforeExpr": false,
        "startsExpr": true,
        "rightAssociative": false,
        "isLoop": false,
        "isAssign": false,
        "prefix": false,
        "postfix": false,
        "binop": null
      },
      "value": "bytes",
      "start": 373,
      "end": 378,
      "loc": {
        "start": {
          "line": 11,
          "column": 39
        },
        "end": {
          "line": 11,
          "column": 44
        }
      }
    },
    {
      "type": {
        "label": ",",
        "beforeExpr": true,
        "startsExpr": false,
        "rightAssociative": false,
        "isLoop": false,
        "isAssign": false,
        "prefix": false,
        "postfix": false,
        "binop": null,
        "updateContext": null
      },
      "start": 378,
      "end": 379,
      "loc": {
        "start": {
          "line": 11,
          "column": 44
        },
        "end": {
          "line": 11,
          "column": 45
        }
      }
    },
    {
      "type": {
        "label": "name",
        "beforeExpr": false,
        "startsExpr": true,
        "rightAssociative": false,
        "isLoop": false,
        "isAssign": false,
        "prefix": false,
        "postfix": false,
        "binop": null
      },
      "value": "position",
      "start": 380,
      "end": 388,
      "loc": {
        "start": {
          "line": 11,
          "column": 46
        },
        "end": {
          "line": 11,
          "column": 54
        }
      }
    },
    {
      "type": {
        "label": ")",
        "beforeExpr": false,
        "startsExpr": false,
        "rightAssociative": false,
        "isLoop": false,
        "isAssign": false,
        "prefix": false,
        "postfix": false,
        "binop": null
      },
      "start": 388,
      "end": 389,
      "loc": {
        "start": {
          "line": 11,
          "column": 54
        },
        "end": {
          "line": 11,
          "column": 55
        }
      }
    },
    {
      "type": {
        "label": ";",
        "beforeExpr": true,
        "startsExpr": false,
        "rightAssociative": false,
        "isLoop": false,
        "isAssign": false,
        "prefix": false,
        "postfix": false,
        "binop": null,
        "updateContext": null
      },
      "start": 389,
      "end": 390,
      "loc": {
        "start": {
          "line": 11,
          "column": 55
        },
        "end": {
          "line": 11,
          "column": 56
        }
      }
    },
    {
      "type": {
        "label": "}",
        "beforeExpr": false,
        "startsExpr": false,
        "rightAssociative": false,
        "isLoop": false,
        "isAssign": false,
        "prefix": false,
        "postfix": false,
        "binop": null
      },
      "start": 393,
      "end": 394,
      "loc": {
        "start": {
          "line": 12,
          "column": 2
        },
        "end": {
          "line": 12,
          "column": 3
        }
      }
    },
    {
      "type": {
        "label": "yield",
        "keyword": "yield",
        "beforeExpr": true,
        "startsExpr": true,
        "rightAssociative": false,
        "isLoop": false,
        "isAssign": false,
        "prefix": false,
        "postfix": false,
        "binop": null,
        "updateContext": null
      },
      "value": "yield",
      "start": 398,
      "end": 403,
      "loc": {
        "start": {
          "line": 14,
          "column": 2
        },
        "end": {
          "line": 14,
          "column": 7
        }
      }
    },
    {
      "type": {
        "label": "name",
        "beforeExpr": false,
        "startsExpr": true,
        "rightAssociative": false,
        "isLoop": false,
        "isAssign": false,
        "prefix": false,
        "postfix": false,
        "binop": null
      },
      "value": "byte2pair",
      "start": 404,
      "end": 413,
      "loc": {
        "start": {
          "line": 14,
          "column": 8
        },
        "end": {
          "line": 14,
          "column": 17
        }
      }
    },
    {
      "type": {
        "label": "[",
        "beforeExpr": true,
        "startsExpr": true,
        "rightAssociative": false,
        "isLoop": false,
        "isAssign": false,
        "prefix": false,
        "postfix": false,
        "binop": null,
        "updateContext": null
      },
      "start": 413,
      "end": 414,
      "loc": {
        "start": {
          "line": 14,
          "column": 17
        },
        "end": {
          "line": 14,
          "column": 18
        }
      }
    },
    {
      "type": {
        "label": "name",
        "beforeExpr": false,
        "startsExpr": true,
        "rightAssociative": false,
        "isLoop": false,
        "isAssign": false,
        "prefix": false,
        "postfix": false,
        "binop": null
      },
      "value": "b",
      "start": 414,
      "end": 415,
      "loc": {
        "start": {
          "line": 14,
          "column": 18
        },
        "end": {
          "line": 14,
          "column": 19
        }
      }
    },
    {
      "type": {
        "label": "]",
        "beforeExpr": false,
        "startsExpr": false,
        "rightAssociative": false,
        "isLoop": false,
        "isAssign": false,
        "prefix": false,
        "postfix": false,
        "binop": null,
        "updateContext": null
      },
      "start": 415,
      "end": 416,
      "loc": {
        "start": {
          "line": 14,
          "column": 19
        },
        "end": {
          "line": 14,
          "column": 20
        }
      }
    },
    {
      "type": {
        "label": ";",
        "beforeExpr": true,
        "startsExpr": false,
        "rightAssociative": false,
        "isLoop": false,
        "isAssign": false,
        "prefix": false,
        "postfix": false,
        "binop": null,
        "updateContext": null
      },
      "start": 416,
      "end": 417,
      "loc": {
        "start": {
          "line": 14,
          "column": 20
        },
        "end": {
          "line": 14,
          "column": 21
        }
      }
    },
    {
      "type": {
        "label": "++/--",
        "beforeExpr": false,
        "startsExpr": true,
        "rightAssociative": false,
        "isLoop": false,
        "isAssign": false,
        "prefix": true,
        "postfix": true,
        "binop": null
      },
      "value": "++",
      "start": 421,
      "end": 423,
      "loc": {
        "start": {
          "line": 16,
          "column": 2
        },
        "end": {
          "line": 16,
          "column": 4
        }
      }
    },
    {
      "type": {
        "label": "name",
        "beforeExpr": false,
        "startsExpr": true,
        "rightAssociative": false,
        "isLoop": false,
        "isAssign": false,
        "prefix": false,
        "postfix": false,
        "binop": null
      },
      "value": "start",
      "start": 423,
      "end": 428,
      "loc": {
        "start": {
          "line": 16,
          "column": 4
        },
        "end": {
          "line": 16,
          "column": 9
        }
      }
    },
    {
      "type": {
        "label": ";",
        "beforeExpr": true,
        "startsExpr": false,
        "rightAssociative": false,
        "isLoop": false,
        "isAssign": false,
        "prefix": false,
        "postfix": false,
        "binop": null,
        "updateContext": null
      },
      "start": 428,
      "end": 429,
      "loc": {
        "start": {
          "line": 16,
          "column": 9
        },
        "end": {
          "line": 16,
          "column": 10
        }
      }
    },
    {
      "type": {
        "label": "}",
        "beforeExpr": false,
        "startsExpr": false,
        "rightAssociative": false,
        "isLoop": false,
        "isAssign": false,
        "prefix": false,
        "postfix": false,
        "binop": null
      },
      "start": 431,
      "end": 432,
      "loc": {
        "start": {
          "line": 17,
          "column": 1
        },
        "end": {
          "line": 17,
          "column": 2
        }
      }
    },
    {
      "type": {
        "label": "}",
        "beforeExpr": false,
        "startsExpr": false,
        "rightAssociative": false,
        "isLoop": false,
        "isAssign": false,
        "prefix": false,
        "postfix": false,
        "binop": null
      },
      "start": 433,
      "end": 434,
      "loc": {
        "start": {
          "line": 18,
          "column": 0
        },
        "end": {
          "line": 18,
          "column": 1
        }
      }
    },
    {
      "type": {
        "label": "eof",
        "beforeExpr": false,
        "startsExpr": false,
        "rightAssociative": false,
        "isLoop": false,
        "isAssign": false,
        "prefix": false,
        "postfix": false,
        "binop": null,
        "updateContext": null
      },
      "start": 435,
      "end": 435,
      "loc": {
        "start": {
          "line": 19,
          "column": 0
        },
        "end": {
          "line": 19,
          "column": 0
        }
      }
    }
  ]
}